include_stubs/__init__.py
include_stubs/_version.py
include_stubs/cli.py
include_stubs/config.py
include_stubs/logging.py
include_stubs/plugin.py
include_stubs/utils.py
mkdocs_include_stubs_plugin-1.0.2.dist-info/licenses/LICENSE
mkdocs_include_stubs_plugin-1.0.2.dist-info/METADATA
mkdocs_include_stubs_plugin-1.0.2.dist-info/WHEEL
mkdocs_include_stubs_plugin-1.0.2.dist-info/entry_points.txt
mkdocs_include_stubs_plugin-1.0.2.dist-info/top_level.txt
mkdocs_include_stubs_plugin-1.0.2.dist-info/RECORD
