Metadata-Version: 2.4
Name: mkdocs-include-stubs-plugin
Version: 1.0.2
Summary: Mkdocs plugin to include stubs (single pages) from multiple GitHub branches of a repo within a mkdocs website build.
Author-email: Davide Marchegiani <davide.marchegiani@anu.edu.au>
Maintainer-email: Davide Marchegiani <davide.marchegiani@anu.edu.au>
License: Apache Software License 2.0
Project-URL: Repository, https://github.com/ACCESS-NRI/mkdocs_include_stubs_plugin
Keywords: mkdocs,plugin,mkdocs plugin,access-nri
Requires-Python: >=3.11
License-File: LICENSE
Requires-Dist: beautifulsoup4>=4.13.4
Requires-Dist: mkdocs>=1.6
Requires-Dist: termcolor>=3.0
Requires-Dist: versioneer>=0.28
Requires-Dist: requests>=2.31.0
Provides-Extra: dev
Requires-Dist: ipykernel>=6.0; extra == "dev"
Requires-Dist: pytest>=8.0; extra == "dev"
Requires-Dist: pytest-cov>=5.0; extra == "dev"
Requires-Dist: pytest-subprocess>=1.5.3; extra == "dev"
Dynamic: license-file
